setup.py
ternya/__init__.py
ternya/annotation.py
ternya/config.py
ternya/exceptions.py
ternya/modules.py
ternya/mq.py
ternya/openstack.py
ternya/process.py
ternya/ternya.py
ternya.egg-info/PKG-INFO
ternya.egg-info/SOURCES.txt
ternya.egg-info/dependency_links.txt
ternya.egg-info/requires.txt
ternya.egg-info/top_level.txt