Metadata-Version: 1.1
Name: ternya
Version: 0.1.2
Summary: lightweight python library for openstack notification
Home-page: https://github.com/ndrlslz/ternya
Author: ndrlslz
Author-email: ndrlslz@163.com
License: MIT
Keywords: openstack notification
Platform: UNKNOWN
Classifier: Development Status :: 3 - Alpha
Classifier: Intended Audience :: Developers
Classifier: Topic :: Software Development :: Libraries :: Python Modules
Classifier: License :: OSI Approved :: MIT License
Classifier: Programming Language :: Python :: 3
